tno/quantum/problems/n_minus_1/__init__.py
tno/quantum/problems/n_minus_1/_utils.py
tno/quantum/problems/n_minus_1/py.typed
tno/quantum/problems/n_minus_1/gate_based/__init__.py
tno/quantum/problems/n_minus_1/gate_based/_circuit_factory.py
tno/quantum/problems/n_minus_1/gate_based/_gate_based_n1_solver.py
tno/quantum/problems/n_minus_1/gate_based/_gates/__init__.py
tno/quantum/problems/n_minus_1/gate_based/_gates/amplitude_amplification.py
tno/quantum/problems/n_minus_1/gate_based/_gates/oracle.py
tno/quantum/problems/n_minus_1/gate_based/_gates/utils.py
tno/quantum/problems/n_minus_1/gate_based/_utils/__init__.py
tno/quantum/problems/n_minus_1/gate_based/_utils/encode_graph.py
tno/quantum/problems/n_minus_1/io/__init__.py
tno/quantum/problems/n_minus_1/io/_graphs_io.py
tno/quantum/problems/n_minus_1/quantum_annealing/__init__.py
tno/quantum/problems/n_minus_1/quantum_annealing/_qa_based_n1_solver.py
tno/quantum/problems/n_minus_1/quantum_annealing/_bqm_factories/__init__.py
tno/quantum/problems/n_minus_1/quantum_annealing/_bqm_factories/layers_factory.py
tno/quantum/problems/n_minus_1/quantum_annealing/_bqm_factories/loadflow_factory.py
tno/quantum/problems/n_minus_1/quantum_annealing/_bqm_factories/nmo_factory.py
tno/quantum/problems/n_minus_1/quantum_annealing/_bqm_factories/utils.py
tno/quantum/problems/n_minus_1/quantum_annealing/_containers/__init__.py
tno/quantum/problems/n_minus_1/quantum_annealing/_containers/decoded_result.py
tno/quantum/problems/n_minus_1/quantum_annealing/_containers/results_overview.py
tno/quantum/problems/n_minus_1/quantum_annealing/datasets/__init__.py
tno/quantum/problems/n_minus_1/quantum_annealing/datasets/_load_data.py
tno/quantum/problems/n_minus_1/quantum_annealing/datasets/_data/__init__.py
tno/quantum/problems/n_minus_1/quantum_annealing/datasets/_data/medium_dataset.gml.gz
tno/quantum/problems/n_minus_1/quantum_annealing/datasets/_data/small_dataset.gml.gz
tno/quantum/problems/n_minus_1/test/__init__.py
tno_quantum_problems_n_minus_1-1.0.0.dist-info/licenses/LICENSE
tno_quantum_problems_n_minus_1-1.0.0.dist-info/METADATA
tno_quantum_problems_n_minus_1-1.0.0.dist-info/WHEEL
tno_quantum_problems_n_minus_1-1.0.0.dist-info/top_level.txt
tno_quantum_problems_n_minus_1-1.0.0.dist-info/RECORD
