Metadata-Version: 2.4
Name: tno.quantum.problems.n_minus_1
Version: 1.0.0
Summary: N-1 quantum based solver 
Author-email: TNO Quantum Code Lab <tnoquantum@tno.nl>
Maintainer-email: TNO Quantum Code Lab <tnoquantum@tno.nl>
License: Apache License, Version 2.0
Project-URL: Homepage, https://github.com/TNO-Quantum/
Project-URL: Documentation, https://github.com/TNO-Quantum/documentation
Project-URL: Source, https://github.com/TNO-Quantum/problems.n_minus_one
Keywords: TNO,Quantum,N-1 problem,QUBO,Quantum Annealing,Gate based
Platform: any
Classifier: License :: OSI Approved :: Apache Software License
Classifier: Programming Language :: Python :: 3
Classifier: Programming Language :: Python :: 3.9
Classifier: Programming Language :: Python :: 3.10
Classifier: Programming Language :: Python :: 3.11
Classifier: Programming Language :: Python :: 3.12
Classifier: Programming Language :: Python :: 3.13
Classifier: Operating System :: OS Independent
Classifier: Intended Audience :: Developers
Classifier: Intended Audience :: Information Technology
Classifier: Intended Audience :: Science/Research
Classifier: Typing :: Typed
Requires-Python: >=3.9
License-File: LICENSE
Requires-Dist: numpy
Requires-Dist: networkx
Requires-Dist: matplotlib
Requires-Dist: scipy
Requires-Dist: pandas
Requires-Dist: tno.quantum.optimization.qubo[dwave]~=1.0
Requires-Dist: qiskit>=1.0.1
Requires-Dist: qiskit_aer>=0.13.1
Provides-Extra: tests
Requires-Dist: pytest>=8.1.1; extra == "tests"
Requires-Dist: pytest-cov>=4.1.0; extra == "tests"
Requires-Dist: tomlkit; extra == "tests"
Dynamic: license-file
